PyMind.egg-info/PKG-INFO
PyMind.egg-info/SOURCES.txt
PyMind.egg-info/dependency_links.txt
PyMind.egg-info/entry_points.txt
PyMind.egg-info/requires.txt
PyMind.egg-info/top_level.txt
app/PyMind/__init__.py
app/PyMind/edit.py
app/PyMind/map_print.py
app/PyMind/ops.py
app/PyMind/pymind.py
app/PyMind/settings.py