Metadata-Version: 1.1
Name: PyMind
Version: 1.4.1
Summary: Unofficial Mindmeister command line tool.
Home-page: http://kayrick-lair.blogspot.com/search/label/PyMind
Author: Alexey Kravets
Author-email: mr.kayrick@gmail.com
License: GPL3
Keywords: mindmeister,mindmaps
Platform: UNKNOWN
Classifier: Development Status :: 4 - Beta
Classifier: Topic :: Internet :: WWW/HTTP
Classifier: Environment :: Console :: Curses
Classifier: License :: OSI Approved :: GNU General Public License (GPL)
